meta_monsterkong/__init__.py
meta_monsterkong/board.py
meta_monsterkong/camera.py
meta_monsterkong/coin.py
meta_monsterkong/envs.py
meta_monsterkong/fireball.py
meta_monsterkong/ladder.py
meta_monsterkong/make_env.py
meta_monsterkong/monsterPerson.py
meta_monsterkong/onBoard.py
meta_monsterkong/person.py
meta_monsterkong/player.py
meta_monsterkong/side_collisions.py
meta_monsterkong/wall.py
meta_monsterkong/wrappers.py
meta_monsterkong/assets/background.png
meta_monsterkong/assets/boundary.png
meta_monsterkong/assets/coin1.png
meta_monsterkong/assets/coin2.png
meta_monsterkong/assets/coin3.png
meta_monsterkong/assets/coin4.png
meta_monsterkong/assets/coin5.png
meta_monsterkong/assets/enemy1.png
meta_monsterkong/assets/fire.png
meta_monsterkong/assets/fireballdown.png
meta_monsterkong/assets/fireballleft.png
meta_monsterkong/assets/fireballright.png
meta_monsterkong/assets/ladder copy.png
meta_monsterkong/assets/ladder.png
meta_monsterkong/assets/left.png
meta_monsterkong/assets/left2.png
meta_monsterkong/assets/monster0.png
meta_monsterkong/assets/monster01.png
meta_monsterkong/assets/monster1.png
meta_monsterkong/assets/monster11.png
meta_monsterkong/assets/monster2.png
meta_monsterkong/assets/monster21.png
meta_monsterkong/assets/monster3.png
meta_monsterkong/assets/monster31.png
meta_monsterkong/assets/monsterstill0.png
meta_monsterkong/assets/monsterstill1.png
meta_monsterkong/assets/monsterstill10.png
meta_monsterkong/assets/monsterstill11.png
meta_monsterkong/assets/princess copy.png
meta_monsterkong/assets/princess.png
meta_monsterkong/assets/right.png
meta_monsterkong/assets/right2.png
meta_monsterkong/assets/spikes.png
meta_monsterkong/assets/still.png
meta_monsterkong/assets/still2.png
meta_monsterkong/assets/wood_block copy.png
meta_monsterkong/assets/wood_block.png
meta_monsterkong/assets/wood_block1.png
meta_monsterkong/assets/wood_block2.png
meta_monsterkong/assets/wood_block3.png
meta_monsterkong/assets/wood_block4.png
meta_monsterkong-0.0.1.dist-info/METADATA
meta_monsterkong-0.0.1.dist-info/WHEEL
meta_monsterkong-0.0.1.dist-info/dependency_links.txt
meta_monsterkong-0.0.1.dist-info/top_level.txt
meta_monsterkong-0.0.1.dist-info/RECORD
